jupyterlab_asksmce_voat/__init__.py
jupyterlab_asksmce_voat/_version.py
jupyterlab_asksmce_voat/labextension/build_log.json
jupyterlab_asksmce_voat/labextension/package.json
jupyterlab_asksmce_voat/labextension/schemas/jupyterlab_asksmce_voat/package.json.orig
jupyterlab_asksmce_voat/labextension/schemas/jupyterlab_asksmce_voat/plugin.json
jupyterlab_asksmce_voat/labextension/static/fb29b6ad8cd60b9112b8c9b51c8b3b5ad3b87e8e128700a4b9033bbf7d3978c0.png
jupyterlab_asksmce_voat/labextension/static/lib_index_js.0e6441b8d9d80d900d53.js
jupyterlab_asksmce_voat/labextension/static/lib_index_js.0e6441b8d9d80d900d53.js.map
jupyterlab_asksmce_voat/labextension/static/node_modules_babel_runtime_helpers_esm_extends_js-node_modules_emotion_memoize_dist_emotion-m-27ec560.139e3c16e625f53b8648.js
jupyterlab_asksmce_voat/labextension/static/node_modules_babel_runtime_helpers_esm_extends_js-node_modules_emotion_memoize_dist_emotion-m-27ec560.139e3c16e625f53b8648.js.map
jupyterlab_asksmce_voat/labextension/static/node_modules_babel_runtime_helpers_esm_extends_js-node_modules_emotion_memoize_dist_emotion-m-27ec561.43bc32ab94686dcf0e3c.js
jupyterlab_asksmce_voat/labextension/static/node_modules_babel_runtime_helpers_esm_extends_js-node_modules_emotion_memoize_dist_emotion-m-27ec561.43bc32ab94686dcf0e3c.js.map
jupyterlab_asksmce_voat/labextension/static/remoteEntry.980fb92049a1fbc63351.js
jupyterlab_asksmce_voat/labextension/static/remoteEntry.980fb92049a1fbc63351.js.map
jupyterlab_asksmce_voat/labextension/static/style.js
jupyterlab_asksmce_voat/labextension/static/style_index_css.2e04fda4d3288d30ff75.js
jupyterlab_asksmce_voat/labextension/static/style_index_css.2e04fda4d3288d30ff75.js.map
jupyterlab_asksmce_voat/labextension/static/vendors-node_modules_css-loader_dist_runtime_api_js-node_modules_css-loader_dist_runtime_cssW-72eba1.bc54cf484ac43744f9e2.js
jupyterlab_asksmce_voat-0.1.12.dist-info/METADATA
jupyterlab_asksmce_voat-0.1.12.dist-info/WHEEL
jupyterlab_asksmce_voat-0.1.12.dist-info/licenses/LICENSE
jupyterlab_asksmce_voat-0.1.12.dist-info/RECORD
